README.md
setup.py
dis_pydactyl.egg-info/PKG-INFO
dis_pydactyl.egg-info/SOURCES.txt
dis_pydactyl.egg-info/dependency_links.txt
dis_pydactyl.egg-info/requires.txt
dis_pydactyl.egg-info/top_level.txt
dispydactyl/__init__.py
dispydactyl/client.py
dispydactyl/constants.py
dispydactyl/exceptions.py
dispydactyl/responses.py
dispydactyl/api/__init__.py
dispydactyl/api/base.py
dispydactyl/api/client.py
dispydactyl/api/locations.py
dispydactyl/api/nests.py
dispydactyl/api/nodes.py
dispydactyl/api/servers.py
dispydactyl/api/user.py