Metadata-Version: 2.1
Name: dis-pydactyl
Version: 0.1.15
Summary: An easy to use Python wrapper for the Pterodactyl Panel API.
Home-page: https://github.com/Dishit79/DisPydactyl
Author: Dishit79
Author-email: Dishit79@gmail.com
License: UNKNOWN
Project-URL: Documentation, https://pydactyl.readthedocs.io/
Project-URL: Source, https://github.com/Dishit79/DisPydactyl
Platform: UNKNOWN
Classifier: Programming Language :: Python :: 3
Classifier: License :: OSI Approved :: MIT License
Classifier: Natural Language :: English
Classifier: Operating System :: OS Independent
Requires-Python: >=3.4
